ComboFinder/__init__.py
ComboFinder-0.1.1.dist-info/LICENSE
ComboFinder-0.1.1.dist-info/METADATA
ComboFinder-0.1.1.dist-info/WHEEL
ComboFinder-0.1.1.dist-info/top_level.txt
ComboFinder-0.1.1.dist-info/RECORD
