Metadata-Version: 2.1
Name: ComboFinder
Version: 0.1.1
Summary: Groups products into combos such that the cummulative price is attractive.
Home-page: https://github.com/WWFelina/ComboFinder
Author: Prabhdeep Singh
Author-email: singh_prabhdeep@outlook.in
License: UNKNOWN
Platform: UNKNOWN
Classifier: Programming Language :: Python :: 3
Classifier: License :: OSI Approved :: MIT License
Classifier: Operating System :: OS Independent
